source code:
```
package org.fenixsoft.clazz;
public class TestClass {
	private int m;
	public int inc() {
		return m + 1;
	}
}
```
class byte code:
```
CAFEBABE0000003400130A0004000F09000300100700110700120100016D010001490100063C696E69743E010003282956010004436F646501000F4C696E654E756D6265725461626C65010003696E6301000328294901000A536F7572636546696C6501000E54657374436C6173732E6A6176610C000700080C0005000601001D6F72672F66656E6978736F66742F636C617A7A2F54657374436C6173730100106A6176612F6C616E672F4F626A6563740021000300040000000100020005000600000002000100070008000100090000001D00010001000000052AB70001B100000001000A000000060001000000020001000B000C000100090000001F00020001000000072AB400020460AC00000001000A000000060001000000050001000D00000002000E
```
### 魔数(Magic Number)
4个字节
```
CAFEBABE
```
### Class文件版本
Minor Version + Major Version
```
00000034
```
Java版本号从45开始，34H即52。我的是JDK版本是1.8.0_201。
### 常量池
常量池的数量是不固定的，入口是两个字节的无符号数，即上面的`0013`，即十进制的19，代表常量池有18个常量，比较特别的是计数是从1开始的，索引值置为0代表不引用任何一个常量池项目。常量池项目类型繁多，每种类型都有自己的结构。

首先看下一字节为`0A`，查书上的表tag为10是`CONSTANT_Methodref_info`，表示类中方法的符号引用，发现这个部分总共占5个字节。即
```
0A 0004 000F
```
`0A`即上面讲的标志位tag，`0004`和`000F`两个索引值分别对应**指向声明方法的类描述符CONSTANT_Class_info的索引项**和**指向名称及类型描述符CONSTANT_NameAndType**的索引项。这个和书上的编译结果略有出入。
***
仔细对比了下，跟书上差的好多。初步可以确定下下面的部分：
```
6F72672F66656E6978736F66742F636C617A7A2F54657374436C617373
```
即为`org/fenixsoft/clazz/TestClass`；
及前面的`01001D`为CONSTANT_Utf8_info，即UTF-8编码的字符串。`01`是tag标志位，`001D`即length，长29个字节，就是上面的那一串：
```
6F72672F66656E6978736F66742F636C617A7A2F54657374436C617373
```
刚好29个字节。

但是中间夹塞的一大串书上没讲到，初步猜想可能是版本变化增加的特性。书上还有个细节没大明白，就是CONSTANT_Class_info的name_index值为0x0002也即指向了常量池中的第二项常量？书上常量池的项目类型比较特殊的是表里面没有对应2的标志位，还有13,14,17。

用javap分析下：
```
E:\Work\myjava>javap -verbose TestClass
警告: 二进制文件TestClass包含org.fenixsoft.clazz.TestClass
Classfile /E:/Work/myjava/TestClass.class
  Last modified 2019-12-19; size 295 bytes
  MD5 checksum ff327e53338de6f5f52ac73c58c0160d
  Compiled from "TestClass.java"
public class org.fenixsoft.clazz.TestClass
  minor version: 0
  major version: 52
  flags: ACC_PUBLIC, ACC_SUPER
Constant pool:
   #1 = Methodref          #4.#15         // java/lang/Object."<init>":()V
   #2 = Fieldref           #3.#16         // org/fenixsoft/clazz/TestClass.m:I
   #3 = Class              #17            // org/fenixsoft/clazz/TestClass
   #4 = Class              #18            // java/lang/Object
   #5 = Utf8               m
   #6 = Utf8               I
   #7 = Utf8               <init>
   #8 = Utf8               ()V
   #9 = Utf8               Code
  #10 = Utf8               LineNumberTable
  #11 = Utf8               inc
  #12 = Utf8               ()I
  #13 = Utf8               SourceFile
  #14 = Utf8               TestClass.java
  #15 = NameAndType        #7:#8          // "<init>":()V
  #16 = NameAndType        #5:#6          // m:I
  #17 = Utf8               org/fenixsoft/clazz/TestClass
  #18 = Utf8               java/lang/Object
{
  public org.fenixsoft.clazz.TestClass();
    descriptor: ()V
    flags: ACC_PUBLIC
    Code:
      stack=1, locals=1, args_size=1
         0: aload_0
         1: invokespecial #1                  // Method java/lang/Object."<init
":()V
         4: return
      LineNumberTable:
        line 2: 0

  public int inc();
    descriptor: ()I
    flags: ACC_PUBLIC
    Code:
      stack=2, locals=1, args_size=1
         0: aload_0
         1: getfield      #2                  // Field m:I
         4: iconst_1
         5: iadd
         6: ireturn
      LineNumberTable:
        line 5: 0
}
SourceFile: "TestClass.java"
```
看到下面这个，果然和我上面示例分析的一致：
```
Constant pool:
   #1 = Methodref          #4.#15         // java/lang/Object."<init>":()V
```
---
### 访问标志(access_flags)
两个字节，定义的标志名称是错位区分定义的。两个字节本来是有16个标志位可以使用，当前用了8个。用于识别一些类或者接口层次的信息。

上面javap编译结果可以看到：
```
flags: ACC_PUBLIC, ACC_SUPER
```
这两个为真，查表对应为`0x0001`和`0x0020`，所以access_flags的值为：0x0001|0x0020 = 0x0021
### 类索引、父索引与接口索引集合
```
   #3 = Class              #17            // org/fenixsoft/clazz/TestClass
   #4 = Class              #18            // java/lang/Object
   #17 = Utf8               org/fenixsoft/clazz/TestClass
   #18 = Utf8               java/lang/Object
```
字节码文件里对应刚好是`0x0021`后面的`\x00\x03\x00\x04\x00\x00`。
